{"version":1,"resource":"file:///home/deeh/.continue/config.yaml","entries":[{"id":"FCaP.yaml","timestamp":1782365081662},{"id":"YI2P.yaml","timestamp":1782365145090},{"id":"Nvgc.yaml","timestamp":1782365296829},{"id":"VeLy.yaml","timestamp":1782365372720},{"id":"eOJ7.yaml","timestamp":1782365826495},{"id":"iHRM.yaml","timestamp":1782366067205},{"id":"pwWB.yaml","timestamp":1782366252564},{"id":"uNrO.yaml","timestamp":1782366532061},{"id":"sIGc.yaml","timestamp":1782366610825},{"id":"hg5F.yaml","timestamp":1782366625626},{"id":"7O0i.yaml","timestamp":1782366741735},{"id":"NYTu.yaml","timestamp":1782366795049}]}